anymlops/__init__.py
anymlops/__main__.py
anymlops/_version.py
anymlops/constants.py
anymlops/cost.py
anymlops/deploy.py
anymlops/deprecate.py
anymlops/destroy.py
anymlops/initialize.py
anymlops/keycloak.py
anymlops/render.py
anymlops/schema.py
anymlops/upgrade.py
anymlops/utils.py
anymlops/version.py
anymlops/cli/__init__.py
anymlops/cli/dev.py
anymlops/cli/init.py
anymlops/cli/keycloak.py
anymlops/cli/main.py
anymlops/provider/__init__.py
anymlops/provider/git.py
anymlops/provider/terraform.py
anymlops/provider/cicd/__init__.py
anymlops/provider/cicd/common.py
anymlops/provider/cicd/github.py
anymlops/provider/cicd/gitlab.py
anymlops/provider/cicd/linter.py
anymlops/provider/cloud/__init__.py
anymlops/provider/cloud/amazon_web_services.py
anymlops/provider/cloud/azure_cloud.py
anymlops/provider/cloud/commons.py
anymlops/provider/cloud/digital_ocean.py
anymlops/provider/cloud/google_cloud.py
anymlops/provider/dns/__init__.py
anymlops/provider/dns/cloudflare.py
anymlops/provider/oauth/__init__.py
anymlops/provider/oauth/auth0.py
anymlops/stages/__init__.py
anymlops/stages/checks.py
anymlops/stages/input_vars.py
anymlops/stages/state_imports.py
anymlops/stages/tf_objects.py
anymlops/template/stages/01-terraform-state/aws/main.tf
anymlops/template/stages/01-terraform-state/aws/modules/terraform-state/main.tf
anymlops/template/stages/01-terraform-state/aws/modules/terraform-state/output.tf
anymlops/template/stages/01-terraform-state/aws/modules/terraform-state/variables.tf
anymlops/template/stages/01-terraform-state/azure/main.tf
anymlops/template/stages/01-terraform-state/azure/modules/terraform-state/main.tf
anymlops/template/stages/01-terraform-state/azure/modules/terraform-state/variables.tf
anymlops/template/stages/01-terraform-state/do/main.tf
anymlops/template/stages/01-terraform-state/do/modules/spaces/main.tf
anymlops/template/stages/01-terraform-state/do/modules/spaces/variables.tf
anymlops/template/stages/01-terraform-state/do/modules/spaces/versions.tf
anymlops-0.1.dist-info/METADATA
anymlops-0.1.dist-info/WHEEL
anymlops-0.1.dist-info/entry_points.txt
anymlops-0.1.dist-info/RECORD
