Metadata-Version: 2.1
Name: anymlops
Version: 0.1
Summary: A data science platform that works.
Project-URL: Documentation, https://www.beartell.com
Project-URL: Source, https://github.com/beartell/anymlops
Author-email: Beartell team <bcakir@beartell.com>
License-Expression: BSD-3-Clause
Keywords: anymlops,aws,azure,dask,do,gcp,jupyter
Classifier: Development Status :: 5 - Production/Stable
Classifier: Framework :: Jupyter :: JupyterLab
Classifier: Intended Audience :: Developers
Classifier: Intended Audience :: Education
Classifier: Intended Audience :: Information Technology
Classifier: Intended Audience :: Science/Research
Classifier: Intended Audience :: System Administrators
Classifier: Programming Language :: Python :: 3
Classifier: Programming Language :: Python :: 3.8
Classifier: Programming Language :: Python :: 3.9
Classifier: Programming Language :: Python :: 3.10
Classifier: Topic :: Software Development :: Build Tools
Requires-Python: >=3.8
Requires-Dist: auth0-python==4.0.0
Requires-Dist: azure-identity==1.6.1
Requires-Dist: azure-mgmt-containerservice==16.2.0
Requires-Dist: bcrypt==4.0.1
Requires-Dist: boto3==1.26.54
Requires-Dist: cloudflare==2.11.1
Requires-Dist: kubernetes==25.3.0
Requires-Dist: pydantic==1.10.4
Requires-Dist: pynacl==1.5.0
Requires-Dist: python-keycloak==2.9.0
Requires-Dist: questionary==1.10.0
Requires-Dist: rich==13.2.0
Requires-Dist: ruamel-yaml==0.17.21
Requires-Dist: typer==0.7.0
Provides-Extra: dev
Requires-Dist: black==22.3.0; extra == 'dev'
Requires-Dist: dask-gateway; extra == 'dev'
Requires-Dist: diagrams; extra == 'dev'
Requires-Dist: escapism; extra == 'dev'
Requires-Dist: flake8==3.8.4; extra == 'dev'
Requires-Dist: importlib-metadata<5.0; extra == 'dev'
Requires-Dist: jhub-client; extra == 'dev'
Requires-Dist: paramiko; extra == 'dev'
Requires-Dist: pre-commit; extra == 'dev'
Requires-Dist: pytest; extra == 'dev'
Requires-Dist: pytest-timeout; extra == 'dev'
